py3wifi/__init__.py
py3wifi/api.py
py3wifi/exceptions.py
py3wifi-0.0.2.dist-info/LICENSE
py3wifi-0.0.2.dist-info/METADATA
py3wifi-0.0.2.dist-info/WHEEL
py3wifi-0.0.2.dist-info/top_level.txt
py3wifi-0.0.2.dist-info/RECORD
