Metadata-Version: 2.1
Name: py3wifi
Version: 0.0.2
Summary: Wrapper for 3WiFi Wireless Database
Home-page: https://github.com/drygdryg/py3wifi
Author: drygdryg
Author-email: drygdryg2014@yandex.com
License: MIT
Download-URL: https://github.com/drygdryg/py3wifi/archive/v0.0.2.zip
Keywords: wrapper api 3wifi
Platform: UNKNOWN
Classifier: License :: OSI Approved :: MIT License
Classifier: Operating System :: OS Independent
Classifier: Programming Language :: Python :: 3.6
Classifier: Programming Language :: Python :: 3.7
Classifier: Programming Language :: Python :: 3.8
Classifier: Topic :: Internet :: WWW/HTTP
Classifier: Topic :: Software Development :: Libraries
Classifier: Intended Audience :: Developers
Classifier: Environment :: Web Environment
Requires-Python: >=3.6
Requires-Dist: requests
